{
    "name": "disk-usage-alert",
    "interval": "1m",
    "rules": [
        {
            "expr": "",
            "for": "5m",
            "keep_firing_for": "0s",
            "grafana_alert": {
                "title": "disk-usage-alert",
                "condition": "C",
                "data": [
                    {
                        "refId": "A",
                        "queryType": "",
                        "relativeTimeRange": {
                            "from": 600,
                            "to": 0
                        },
                        "datasourceUid": "prometheus",
                        "model": {
                            "datasource": {
                                "type": "prometheus",
                                "uid": "prometheus"
                            },
                            "editorMode": "code",
                            "expr": "(1 - node_filesystem_avail_bytes{job=\"node_exporter\", mountpoint=~\"/|/var/lib|/host_mnt/Users\"} / node_filesystem_size_bytes{job=\"node_exporter\", mountpoint=~\"/|/var/lib|/host_mnt/Users\"}) * 100",
                            "instant": false,
                            "intervalMs": 1000,
                            "maxDataPoints": 43200,
                            "range": true,
                            "refId": "A"
                        }
                    },
                    {
                        "refId": "B",
                        "queryType": "",
                        "relativeTimeRange": {
                            "from": 0,
                            "to": 0
                        },
                        "datasourceUid": "__expr__",
                        "model": {
                            "conditions": [
                                {
                                    "evaluator": {
                                        "params": [],
                                        "type": "gt"
                                    },
                                    "operator": {
                                        "type": "and"
                                    },
                                    "query": {
                                        "params": [
                                            "B"
                                        ]
                                    },
                                    "reducer": {
                                        "params": [],
                                        "type": "last"
                                    },
                                    "type": "query"
                                }
                            ],
                            "datasource": {
                                "type": "__expr__",
                                "uid": "__expr__"
                            },
                            "expression": "A",
                            "intervalMs": 1000,
                            "maxDataPoints": 43200,
                            "reducer": "last",
                            "refId": "B",
                            "type": "reduce"
                        }
                    },
                    {
                        "refId": "C",
                        "queryType": "",
                        "relativeTimeRange": {
                            "from": 0,
                            "to": 0
                        },
                        "datasourceUid": "__expr__",
                        "model": {
                            "conditions": [
                                {
                                    "evaluator": {
                                        "params": [
                                            60
                                        ],
                                        "type": "gt"
                                    },
                                    "operator": {
                                        "type": "and"
                                    },
                                    "query": {
                                        "params": [
                                            "C"
                                        ]
                                    },
                                    "reducer": {
                                        "params": [],
                                        "type": "last"
                                    },
                                    "type": "query"
                                }
                            ],
                            "datasource": {
                                "type": "__expr__",
                                "uid": "__expr__"
                            },
                            "expression": "B",
                            "intervalMs": 1000,
                            "maxDataPoints": 43200,
                            "refId": "C",
                            "type": "threshold"
                        }
                    }
                ],
                "no_data_state": "OK",
                "exec_err_state": "Error"
            },
            "annotations": {
                "summary": "High Disk Usage detected: {{ $values.B.Value | printf \"%.2f\" }}%",
                "description": "Server Disk usage on {{ $labels.mountpoint }} is above threshold on instance {{ $labels.instance }}."
            },
            "labels": {
                "severity": "warning",
                "notify_policy": "fast"
            }
        }
    ]
}